fstringinterpolation.py
fstringinterpolation-0.1.1.dist-info/METADATA
fstringinterpolation-0.1.1.dist-info/WHEEL
fstringinterpolation-0.1.1.dist-info/top_level.txt
fstringinterpolation-0.1.1.dist-info/RECORD
