Metadata-Version: 2.4
Name: FStringInterpolation
Version: 0.1.1
Summary: interpolation for python's `configparser` that does f-string substitution
Author-email: IOhannes m zmölnig <zmoelnig@iem.at>
License-Expression: BSD-3-Clause
Project-URL: Homepage, https://github.com/umlaeute/FStringInterpolation
Project-URL: Repository, https://github.com/umlaeute/FStringInterpolation.git
Project-URL: Issues, https://github.com/umlaeute/FStringInterpolation/issues
Classifier: Programming Language :: Python :: 3
Classifier: Operating System :: OS Independent
Classifier: Topic :: Software Development :: Libraries :: Python Modules
Requires-Python: >=3.6
